{
    "$schema": "http://json-schema.org/draft-04/schema#",
    "id": "https://analyticalgraphicsinc.github.io/czml-writer/Schema/InterpolatableProperty.json",
    "title": "InterpolatableProperty",
    "description": "The base schema for a property whose value may be determined by interpolating over provided time-tagged samples.",
    "properties": {
        "epoch": {
            "description": "The epoch to use for times specified as seconds since an epoch.",
            "type": "string",
            "format": "date-time"
        },
        "interpolationAlgorithm": {
            "description": "The interpolation algorithm to use when interpolating. Valid values are \"LINEAR\", \"LAGRANGE\", and \"HERMITE\".",
            "type": "string",
            "default": "LINEAR"
        },
        "interpolationDegree": {
            "description": "The degree of interpolation to use when interpolating.",
            "type": "number",
            "default": 1
        },
        "forwardExtrapolationType": {
            "description": "The type of extrapolation to perform when a value is requested at a time after any available samples. Valid values are \"NONE\", \"HOLD\", and \"EXTRAPOLATE\".",
            "type": "string",
            "default": "NONE"
        },
        "forwardExtrapolationDuration": {
            "description": "The amount of time to extrapolate forward before the property becomes undefined.  A value of 0 will extrapolate forever.",
            "type": "number",
            "default": 0
        },
        "backwardExtrapolationType": {
            "description": "The type of extrapolation to perform when a value is requested at a time before any available samples. Valid values are \"NONE\", \"HOLD\", and \"EXTRAPOLATE\".",
            "type": "string",
            "default": "NONE"
        },
        "backwardExtrapolationDuration": {
            "description": "The amount of time to extrapolate backward before the property becomes undefined.  A value of 0 will extrapolate forever.",
            "type": "number",
            "default": 0
        }
    }
}