{
    "$schema": "http://json-schema.org/draft-07/schema#",
    "$id": "https://analyticalgraphicsinc.github.io/czml-writer/Schema/String.json",
    "title": "String",
    "description": "A string value. The string can optionally vary with time.",
    "type": [
        "array",
        "object",
        "string"
    ],
    "items": {
        "$ref": "#"
    },
    "properties": {
        "string": {
            "$ref": "StringValue.json",
            "description": "The string value.",
            "czmlValue": true
        },
        "reference": {
            "$ref": "ReferenceValue.json",
            "description": "The string specified as a reference to another property.",
            "czmlValue": true
        },
        "delete": {
            "description": "Whether the client should delete existing data for this property. Data will be deleted for the containing interval, or if there is no containing interval, then all data. If true, all other properties in this property will be ignored.",
            "type": "boolean"
        }
    }
}